NeuroPrep/__init__.py
NeuroPrep/utils.py
NeuroPreprocessing/__init__.py
NeuroPreprocessing/utils.py
NeuroPreprocessing-0.1.0.dist-info/LICENSE
NeuroPreprocessing-0.1.0.dist-info/METADATA
NeuroPreprocessing-0.1.0.dist-info/WHEEL
NeuroPreprocessing-0.1.0.dist-info/top_level.txt
NeuroPreprocessing-0.1.0.dist-info/RECORD
