Metadata-Version: 2.1
Name: NeuroPreprocessing
Version: 0.1.0
Author: Anwar Said
Author-email: anwar.said@vanderbilt.edu
Keywords: python,neuroimaging
Classifier: Development Status :: 5 - Production/Stable
Classifier: Intended Audience :: Science/Research
Classifier: License :: OSI Approved :: MIT License
Classifier: Programming Language :: Python :: 3
Classifier: Topic :: Scientific/Engineering
License-File: LICENSE
Requires-Dist: numpy
Requires-Dist: nilearn
Requires-Dist: sphinx-rtd-theme
